crocodile/__init__.py
crocodile/core.py
crocodile/croshell.py
crocodile/database.py
crocodile/deeplearning.py
crocodile/deeplearning_df.py
crocodile/deeplearning_pytorch_template.py
crocodile/deeplearning_template.py
crocodile/deeplearning_torch.py
crocodile/deeplearning_torch2.py
crocodile/environment.py
crocodile/file_management.py
crocodile/matplotlib_management.py
crocodile/meta.py
crocodile/plotly_management.py
crocodile/toolbox.py
crocodile/art/fat_croco
crocodile/art/halfwit_croco
crocodile/art/happy_croco
crocodile/art/water_croco
crocodile/comms/__init__.py
crocodile/comms/notification.py
crocodile/core_modules/__init__.py
crocodile/core_modules/core_1.py
crocodile/core_modules/core_2.py
crocodile/core_modules/core_3.py
crocodile/core_modules/core_4.py
crocodile/deeplearning_helpers/__init__.py
crocodile/deeplearning_torch_helpers/__init__.py
crocodile/deeplearning_torch_helpers/dl1.py
crocodile/deeplearning_torch_helpers/dl2.py
crocodile/deeplearning_torch_helpers/onnx_trial.py
crocodile/file_management_helpers/__init__.py
crocodile/file_management_helpers/file1.py
crocodile/file_management_helpers/file2.py
crocodile/file_management_helpers/file3.py
crocodile/file_management_helpers/file4.py
crocodile/file_management_helpers/file5.py
crocodile/meta_helpers/__init__.py
crocodile/meta_helpers/meta1.py
crocodile/meta_helpers/meta11.py
crocodile/meta_helpers/meta2.py
crocodile/meta_helpers/meta3.py
crocodile/meta_helpers/meta4.py
crocodile/meta_helpers/meta5.py
crocodile/msc/__init__.py
crocodile/msc/ascii_art.py
crocodile/msc/df_tutorial.py
crocodile/msc/in_memory_db_trial.py
crocodile/msc/numerical.py
crocodile/msc/obfuscater.py
crocodile/msc/odds.py
crocodile/msc/yt_download.py
crocodile-15.0.dist-info/METADATA
crocodile-15.0.dist-info/WHEEL
crocodile-15.0.dist-info/top_level.txt
crocodile-15.0.dist-info/RECORD
