Metadata-Version: 2.4
Name: crocodile
Version: 15.0
Summary: Deep Learning Framework & Workload Management For On-premise Personal Machines.
Author-email: Alex Al-Saffar <programmer@usa.com>
License-Expression: MIT AND (Apache-2.0 OR BSD-2-Clause)
Project-URL: Homepage, https://github.com/thisismygitrepo/crocodile
Project-URL: Bug Tracker, https://github.com/thisismygitrepo/crocodile/issues
Project-URL: Documentation, https://crocodile.readthedocs.io/en/latest/
Project-URL: Source Code, https://github.com/thisismygitrepo/crocodile
Project-URL: PyPI, https://pypi.org/project/crocodile
Classifier: Programming Language :: Python :: 3
Classifier: Operating System :: OS Independent
Requires-Python: >=3.13
Requires-Dist: bcrypt>=4.3.0
Requires-Dist: cryptography>=45.0.7
Requires-Dist: colorlog>=6.9.0
Requires-Dist: distro>=1.9.0
Requires-Dist: fire>=0.7.1
Requires-Dist: gitpython>=3.1.45
Requires-Dist: joblib>=1.5.2
Requires-Dist: matplotlib>=3.10.6
Requires-Dist: numpy<=2.2.6
Requires-Dist: orjson>=3.11.3
Requires-Dist: paramiko>=4.0.0
Requires-Dist: plotly>=6.3.0
Requires-Dist: psutil>=7.0.0
Requires-Dist: randomname>=0.2.1
Requires-Dist: requests>=2.32.3
Requires-Dist: rich>=14.1.0
Requires-Dist: sqlalchemy>=2.0.43
Requires-Dist: duckdb-engine>=0.17.0
Requires-Dist: polars>=1.33.0
Requires-Dist: tabulate>=0.9.0
Requires-Dist: tomli>=2.2.1
Requires-Dist: tqdm>=4.67.1
Requires-Dist: pyjson5>=1.6.9
Requires-Dist: pyyaml>=6.0.2
Provides-Extra: full
Provides-Extra: docs
Requires-Dist: sphinx>=8.2.3; extra == "docs"
Requires-Dist: sphinx-rtd-theme>=1.2.0; extra == "docs"
Requires-Dist: sphinx-autodoc-typehints>=1.23.0; extra == "docs"
